smalisp/__init__.py
smalisp/__main__.py
smalisp-0.1.0.dist-info/licenses/LICENSE
smalisp-0.1.0.dist-info/METADATA
smalisp-0.1.0.dist-info/WHEEL
smalisp-0.1.0.dist-info/entry_points.txt
smalisp-0.1.0.dist-info/top_level.txt
smalisp-0.1.0.dist-info/RECORD
