Metadata-Version: 2.4
Name: smalisp
Version: 0.1.0
Summary: A very simple language server for smali
Author-email: Abhi <abhi@revengi.in>
License: MIT License
Project-URL: homepage, https://github.com/AbhiTheModder/smalis.git
Project-URL: source, https://github.com/AbhiTheModder/smalis.git
Project-URL: issues, https://github.com/AbhiTheModder/smalis/issues
Classifier: Development Status :: 3 - Alpha
Classifier: Programming Language :: Python :: 3
Classifier: Operating System :: OS Independent
Requires-Python: >=3.9
License-File: LICENSE
Requires-Dist: pygls
Requires-Dist: PyYAML
Provides-Extra: dev
Requires-Dist: ruff; extra == "dev"
Dynamic: license-file
